odoo/addons/product_supplierinfo_for_customer/README.rst
odoo/addons/product_supplierinfo_for_customer/__init__.py
odoo/addons/product_supplierinfo_for_customer/__manifest__.py
odoo/addons/product_supplierinfo_for_customer/demo/product_demo.xml
odoo/addons/product_supplierinfo_for_customer/i18n/de.po
odoo/addons/product_supplierinfo_for_customer/i18n/es.po
odoo/addons/product_supplierinfo_for_customer/i18n/fr.po
odoo/addons/product_supplierinfo_for_customer/i18n/product_supplierinfo_for_customer.pot
odoo/addons/product_supplierinfo_for_customer/i18n/sl.po
odoo/addons/product_supplierinfo_for_customer/models/__init__.py
odoo/addons/product_supplierinfo_for_customer/models/pricelist.py
odoo/addons/product_supplierinfo_for_customer/models/product_product.py
odoo/addons/product_supplierinfo_for_customer/models/product_supplierinfo.py
odoo/addons/product_supplierinfo_for_customer/models/product_template.py
odoo/addons/product_supplierinfo_for_customer/models/res_partner.py
odoo/addons/product_supplierinfo_for_customer/readme/CONFIGURE.rst
odoo/addons/product_supplierinfo_for_customer/readme/CONTRIBUTORS.rst
odoo/addons/product_supplierinfo_for_customer/readme/DESCRIPTION.rst
odoo/addons/product_supplierinfo_for_customer/readme/ROADMAP.rst
odoo/addons/product_supplierinfo_for_customer/readme/USAGE.rst
odoo/addons/product_supplierinfo_for_customer/static/description/icon.png
odoo/addons/product_supplierinfo_for_customer/static/description/index.html
odoo/addons/product_supplierinfo_for_customer/tests/__init__.py
odoo/addons/product_supplierinfo_for_customer/tests/test_product_supplierinfo_for_customer.py
odoo/addons/product_supplierinfo_for_customer/views/product_view.xml
odoo11_addon_product_supplierinfo_for_customer-11.0.1.0.0.99.dev17.dist-info/METADATA
odoo11_addon_product_supplierinfo_for_customer-11.0.1.0.0.99.dev17.dist-info/WHEEL
odoo11_addon_product_supplierinfo_for_customer-11.0.1.0.0.99.dev17.dist-info/top_level.txt
odoo11_addon_product_supplierinfo_for_customer-11.0.1.0.0.99.dev17.dist-info/RECORD
